{
  "experiment": "data_scarce",
  "years": 5,
  "n_basins": 50,
  "train_samples": 82300,
  "train_period": "1980-10-01 to 1985-09-30",
  "test_nse": 0.7780553102493286,
  "q_cal": 0.16887584328651428,
  "n_params": 82691,
  "best_epoch": 30,
  "train_time_s": 76.8374993801117,
  "test_uncalibrated": {
    "picp": 0.7200482825457436,
    "target_coverage": 0.9,
    "mpiw": 0.7699500918388367,
    "winkler_score": 2.325803518295288,
    "coverage_low_flow": 0.8098653447245368,
    "coverage_normal_flow": 0.6473359851136111,
    "coverage_high_flow": 0.7050970873786407
  },
  "test_calibrated": {
    "picp": 0.8622554680563373,
    "target_coverage": 0.9,
    "mpiw": 1.1077017784118652,
    "winkler_score": 1.9940614700317383,
    "coverage_low_flow": 0.9300355096157227,
    "coverage_normal_flow": 0.8548747802038342,
    "coverage_high_flow": 0.8020437596735612
  },
  "timestamp": "2026-07-06T07:55:08.946825"
}